{
  "file": "/Users/wassimchegham/Sandbox/oss/perfy/public/reports/rc-no-component_2016-11-24/rc-no-component.json",
  "description": {
    "id": "rc-no-component",
    "metrics": {
      "scriptTime": "script execution time in ms, including gc and render",
      "pureScriptTime": "script execution time in ms, without gc nor render",
      "renderTime": "render time in ms",
      "gcTime": "gc time in ms",
      "gcAmount": "gc amount in kbytes",
      "majorGcTime": "time of major gcs in ms",
      "forcedGcTime": "forced gc time in ms",
      "forcedGcAmount": "forced gc amount in kbytes"
    },
    "description": {
      "forceGc": true,
      "userAgent": "Mozilla/5.0 (Macintosh; Intel Mac OS X 10_12_1) AppleWebKit/537.36 (KHTML, like Gecko) Chrome/55.0.2883.95 Safari/537.36",
      "sampleSize": 20,
      "regressionSlopeMetric": "renderTime"
    }
  },
  "stats": {
    "forcedGcAmount": "137.34+-21%",
    "forcedGcTime": "2.73+-17%",
    "gcAmount": "0.00",
    "gcTime": "0.00",
    "majorGcTime": "0.00",
    "pureScriptTime": "0.00",
    "renderTime": "0.00",
    "scriptTime": "0.00"
  },
  "completeSample": [
    {
      "runIndex": 0,
      "timeStamp": "2016-12-24T00:26:54.644Z",
      "values": {
        "scriptTime": 0,
        "pureScriptTime": 0,
        "gcTime": 0,
        "majorGcTime": 0,
        "gcAmount": 0,
        "renderTime": 0,
        "forcedGcTime": 4.531000003218651,
        "forcedGcAmount": 49.488
      }
    },
    {
      "runIndex": 1,
      "timeStamp": "2016-12-24T00:26:54.685Z",
      "values": {
        "scriptTime": 0,
        "pureScriptTime": 0,
        "gcTime": 0,
        "majorGcTime": 0,
        "gcAmount": 0,
        "renderTime": 0,
        "forcedGcTime": 2.3579999953508377,
        "forcedGcAmount": 83.688
      }
    },
    {
      "runIndex": 2,
      "timeStamp": "2016-12-24T00:26:54.728Z",
      "values": {
        "scriptTime": 0,
        "pureScriptTime": 0,
        "gcTime": 0,
        "majorGcTime": 0,
        "gcAmount": 0,
        "renderTime": 0,
        "forcedGcTime": 2.5490000024437904,
        "forcedGcAmount": 218.248
      }
    },
    {
      "runIndex": 3,
      "timeStamp": "2016-12-24T00:26:54.769Z",
      "values": {
        "scriptTime": 0,
        "pureScriptTime": 0,
        "gcTime": 0,
        "majorGcTime": 0,
        "gcAmount": 0,
        "renderTime": 0,
        "forcedGcTime": 2.8909999951720238,
        "forcedGcAmount": 144.408
      }
    },
    {
      "runIndex": 4,
      "timeStamp": "2016-12-24T00:26:54.814Z",
      "values": {
        "scriptTime": 0,
        "pureScriptTime": 0,
        "gcTime": 0,
        "majorGcTime": 0,
        "gcAmount": 0,
        "renderTime": 0,
        "forcedGcTime": 2.9499999955296516,
        "forcedGcAmount": 144.656
      }
    },
    {
      "runIndex": 5,
      "timeStamp": "2016-12-24T00:26:54.867Z",
      "values": {
        "scriptTime": 0,
        "pureScriptTime": 0,
        "gcTime": 0,
        "majorGcTime": 0,
        "gcAmount": 0,
        "renderTime": 0,
        "forcedGcTime": 2.7899999991059303,
        "forcedGcAmount": 140.104
      }
    },
    {
      "runIndex": 6,
      "timeStamp": "2016-12-24T00:26:54.908Z",
      "values": {
        "scriptTime": 0,
        "pureScriptTime": 0,
        "gcTime": 0,
        "majorGcTime": 0,
        "gcAmount": 0,
        "renderTime": 0,
        "forcedGcTime": 2.657999999821186,
        "forcedGcAmount": 142.36
      }
    },
    {
      "runIndex": 7,
      "timeStamp": "2016-12-24T00:26:54.945Z",
      "values": {
        "scriptTime": 0,
        "pureScriptTime": 0,
        "gcTime": 0,
        "majorGcTime": 0,
        "gcAmount": 0,
        "renderTime": 0,
        "forcedGcTime": 2.644999995827675,
        "forcedGcAmount": 140.048
      }
    },
    {
      "runIndex": 8,
      "timeStamp": "2016-12-24T00:26:54.984Z",
      "values": {
        "scriptTime": 0,
        "pureScriptTime": 0,
        "gcTime": 0,
        "majorGcTime": 0,
        "gcAmount": 0,
        "renderTime": 0,
        "forcedGcTime": 2.568000003695488,
        "forcedGcAmount": 140.608
      }
    },
    {
      "runIndex": 9,
      "timeStamp": "2016-12-24T00:26:55.024Z",
      "values": {
        "scriptTime": 0,
        "pureScriptTime": 0,
        "gcTime": 0,
        "majorGcTime": 0,
        "gcAmount": 0,
        "renderTime": 0,
        "forcedGcTime": 2.5820000022649765,
        "forcedGcAmount": 140.104
      }
    },
    {
      "runIndex": 10,
      "timeStamp": "2016-12-24T00:26:55.063Z",
      "values": {
        "scriptTime": 0,
        "pureScriptTime": 0,
        "gcTime": 0,
        "majorGcTime": 0,
        "gcAmount": 0,
        "renderTime": 0,
        "forcedGcTime": 2.625,
        "forcedGcAmount": 141.136
      }
    },
    {
      "runIndex": 11,
      "timeStamp": "2016-12-24T00:26:55.109Z",
      "values": {
        "scriptTime": 0,
        "pureScriptTime": 0,
        "gcTime": 0,
        "majorGcTime": 0,
        "gcAmount": 0,
        "renderTime": 0,
        "forcedGcTime": 2.020999997854233,
        "forcedGcAmount": 140.104
      }
    },
    {
      "runIndex": 12,
      "timeStamp": "2016-12-24T00:26:55.146Z",
      "values": {
        "scriptTime": 0,
        "pureScriptTime": 0,
        "gcTime": 0,
        "majorGcTime": 0,
        "gcAmount": 0,
        "renderTime": 0,
        "forcedGcTime": 2.443000003695488,
        "forcedGcAmount": 140.104
      }
    },
    {
      "runIndex": 13,
      "timeStamp": "2016-12-24T00:26:55.185Z",
      "values": {
        "scriptTime": 0,
        "pureScriptTime": 0,
        "gcTime": 0,
        "majorGcTime": 0,
        "gcAmount": 0,
        "renderTime": 0,
        "forcedGcTime": 2.3599999994039536,
        "forcedGcAmount": 140.104
      }
    },
    {
      "runIndex": 14,
      "timeStamp": "2016-12-24T00:26:55.249Z",
      "values": {
        "scriptTime": 0,
        "pureScriptTime": 0,
        "gcTime": 0,
        "majorGcTime": 0,
        "gcAmount": 0,
        "renderTime": 0,
        "forcedGcTime": 2.9149999991059303,
        "forcedGcAmount": 140.104
      }
    },
    {
      "runIndex": 15,
      "timeStamp": "2016-12-24T00:26:55.289Z",
      "values": {
        "scriptTime": 0,
        "pureScriptTime": 0,
        "gcTime": 0,
        "majorGcTime": 0,
        "gcAmount": 0,
        "renderTime": 0,
        "forcedGcTime": 2.739999994635582,
        "forcedGcAmount": 140.104
      }
    },
    {
      "runIndex": 16,
      "timeStamp": "2016-12-24T00:26:55.333Z",
      "values": {
        "scriptTime": 0,
        "pureScriptTime": 0,
        "gcTime": 0,
        "majorGcTime": 0,
        "gcAmount": 0,
        "renderTime": 0,
        "forcedGcTime": 2.563000001013279,
        "forcedGcAmount": 141.056
      }
    },
    {
      "runIndex": 17,
      "timeStamp": "2016-12-24T00:26:55.379Z",
      "values": {
        "scriptTime": 0,
        "pureScriptTime": 0,
        "gcTime": 0,
        "majorGcTime": 0,
        "gcAmount": 0,
        "renderTime": 0,
        "forcedGcTime": 2.656999997794628,
        "forcedGcAmount": 140.088
      }
    },
    {
      "runIndex": 18,
      "timeStamp": "2016-12-24T00:26:55.417Z",
      "values": {
        "scriptTime": 0,
        "pureScriptTime": 0,
        "gcTime": 0,
        "majorGcTime": 0,
        "gcAmount": 0,
        "renderTime": 0,
        "forcedGcTime": 3.2589999958872795,
        "forcedGcAmount": 140.104
      }
    },
    {
      "runIndex": 19,
      "timeStamp": "2016-12-24T00:26:55.459Z",
      "values": {
        "scriptTime": 0,
        "pureScriptTime": 0,
        "gcTime": 0,
        "majorGcTime": 0,
        "gcAmount": 0,
        "renderTime": 0,
        "forcedGcTime": 2.504000000655651,
        "forcedGcAmount": 140.104
      }
    }
  ],
  "validSample": [
    {
      "runIndex": 0,
      "timeStamp": "2016-12-24T00:26:54.644Z",
      "values": {
        "scriptTime": 0,
        "pureScriptTime": 0,
        "gcTime": 0,
        "majorGcTime": 0,
        "gcAmount": 0,
        "renderTime": 0,
        "forcedGcTime": 4.531000003218651,
        "forcedGcAmount": 49.488
      }
    },
    {
      "runIndex": 1,
      "timeStamp": "2016-12-24T00:26:54.685Z",
      "values": {
        "scriptTime": 0,
        "pureScriptTime": 0,
        "gcTime": 0,
        "majorGcTime": 0,
        "gcAmount": 0,
        "renderTime": 0,
        "forcedGcTime": 2.3579999953508377,
        "forcedGcAmount": 83.688
      }
    },
    {
      "runIndex": 2,
      "timeStamp": "2016-12-24T00:26:54.728Z",
      "values": {
        "scriptTime": 0,
        "pureScriptTime": 0,
        "gcTime": 0,
        "majorGcTime": 0,
        "gcAmount": 0,
        "renderTime": 0,
        "forcedGcTime": 2.5490000024437904,
        "forcedGcAmount": 218.248
      }
    },
    {
      "runIndex": 3,
      "timeStamp": "2016-12-24T00:26:54.769Z",
      "values": {
        "scriptTime": 0,
        "pureScriptTime": 0,
        "gcTime": 0,
        "majorGcTime": 0,
        "gcAmount": 0,
        "renderTime": 0,
        "forcedGcTime": 2.8909999951720238,
        "forcedGcAmount": 144.408
      }
    },
    {
      "runIndex": 4,
      "timeStamp": "2016-12-24T00:26:54.814Z",
      "values": {
        "scriptTime": 0,
        "pureScriptTime": 0,
        "gcTime": 0,
        "majorGcTime": 0,
        "gcAmount": 0,
        "renderTime": 0,
        "forcedGcTime": 2.9499999955296516,
        "forcedGcAmount": 144.656
      }
    },
    {
      "runIndex": 5,
      "timeStamp": "2016-12-24T00:26:54.867Z",
      "values": {
        "scriptTime": 0,
        "pureScriptTime": 0,
        "gcTime": 0,
        "majorGcTime": 0,
        "gcAmount": 0,
        "renderTime": 0,
        "forcedGcTime": 2.7899999991059303,
        "forcedGcAmount": 140.104
      }
    },
    {
      "runIndex": 6,
      "timeStamp": "2016-12-24T00:26:54.908Z",
      "values": {
        "scriptTime": 0,
        "pureScriptTime": 0,
        "gcTime": 0,
        "majorGcTime": 0,
        "gcAmount": 0,
        "renderTime": 0,
        "forcedGcTime": 2.657999999821186,
        "forcedGcAmount": 142.36
      }
    },
    {
      "runIndex": 7,
      "timeStamp": "2016-12-24T00:26:54.945Z",
      "values": {
        "scriptTime": 0,
        "pureScriptTime": 0,
        "gcTime": 0,
        "majorGcTime": 0,
        "gcAmount": 0,
        "renderTime": 0,
        "forcedGcTime": 2.644999995827675,
        "forcedGcAmount": 140.048
      }
    },
    {
      "runIndex": 8,
      "timeStamp": "2016-12-24T00:26:54.984Z",
      "values": {
        "scriptTime": 0,
        "pureScriptTime": 0,
        "gcTime": 0,
        "majorGcTime": 0,
        "gcAmount": 0,
        "renderTime": 0,
        "forcedGcTime": 2.568000003695488,
        "forcedGcAmount": 140.608
      }
    },
    {
      "runIndex": 9,
      "timeStamp": "2016-12-24T00:26:55.024Z",
      "values": {
        "scriptTime": 0,
        "pureScriptTime": 0,
        "gcTime": 0,
        "majorGcTime": 0,
        "gcAmount": 0,
        "renderTime": 0,
        "forcedGcTime": 2.5820000022649765,
        "forcedGcAmount": 140.104
      }
    },
    {
      "runIndex": 10,
      "timeStamp": "2016-12-24T00:26:55.063Z",
      "values": {
        "scriptTime": 0,
        "pureScriptTime": 0,
        "gcTime": 0,
        "majorGcTime": 0,
        "gcAmount": 0,
        "renderTime": 0,
        "forcedGcTime": 2.625,
        "forcedGcAmount": 141.136
      }
    },
    {
      "runIndex": 11,
      "timeStamp": "2016-12-24T00:26:55.109Z",
      "values": {
        "scriptTime": 0,
        "pureScriptTime": 0,
        "gcTime": 0,
        "majorGcTime": 0,
        "gcAmount": 0,
        "renderTime": 0,
        "forcedGcTime": 2.020999997854233,
        "forcedGcAmount": 140.104
      }
    },
    {
      "runIndex": 12,
      "timeStamp": "2016-12-24T00:26:55.146Z",
      "values": {
        "scriptTime": 0,
        "pureScriptTime": 0,
        "gcTime": 0,
        "majorGcTime": 0,
        "gcAmount": 0,
        "renderTime": 0,
        "forcedGcTime": 2.443000003695488,
        "forcedGcAmount": 140.104
      }
    },
    {
      "runIndex": 13,
      "timeStamp": "2016-12-24T00:26:55.185Z",
      "values": {
        "scriptTime": 0,
        "pureScriptTime": 0,
        "gcTime": 0,
        "majorGcTime": 0,
        "gcAmount": 0,
        "renderTime": 0,
        "forcedGcTime": 2.3599999994039536,
        "forcedGcAmount": 140.104
      }
    },
    {
      "runIndex": 14,
      "timeStamp": "2016-12-24T00:26:55.249Z",
      "values": {
        "scriptTime": 0,
        "pureScriptTime": 0,
        "gcTime": 0,
        "majorGcTime": 0,
        "gcAmount": 0,
        "renderTime": 0,
        "forcedGcTime": 2.9149999991059303,
        "forcedGcAmount": 140.104
      }
    },
    {
      "runIndex": 15,
      "timeStamp": "2016-12-24T00:26:55.289Z",
      "values": {
        "scriptTime": 0,
        "pureScriptTime": 0,
        "gcTime": 0,
        "majorGcTime": 0,
        "gcAmount": 0,
        "renderTime": 0,
        "forcedGcTime": 2.739999994635582,
        "forcedGcAmount": 140.104
      }
    },
    {
      "runIndex": 16,
      "timeStamp": "2016-12-24T00:26:55.333Z",
      "values": {
        "scriptTime": 0,
        "pureScriptTime": 0,
        "gcTime": 0,
        "majorGcTime": 0,
        "gcAmount": 0,
        "renderTime": 0,
        "forcedGcTime": 2.563000001013279,
        "forcedGcAmount": 141.056
      }
    },
    {
      "runIndex": 17,
      "timeStamp": "2016-12-24T00:26:55.379Z",
      "values": {
        "scriptTime": 0,
        "pureScriptTime": 0,
        "gcTime": 0,
        "majorGcTime": 0,
        "gcAmount": 0,
        "renderTime": 0,
        "forcedGcTime": 2.656999997794628,
        "forcedGcAmount": 140.088
      }
    },
    {
      "runIndex": 18,
      "timeStamp": "2016-12-24T00:26:55.417Z",
      "values": {
        "scriptTime": 0,
        "pureScriptTime": 0,
        "gcTime": 0,
        "majorGcTime": 0,
        "gcAmount": 0,
        "renderTime": 0,
        "forcedGcTime": 3.2589999958872795,
        "forcedGcAmount": 140.104
      }
    },
    {
      "runIndex": 19,
      "timeStamp": "2016-12-24T00:26:55.459Z",
      "values": {
        "scriptTime": 0,
        "pureScriptTime": 0,
        "gcTime": 0,
        "majorGcTime": 0,
        "gcAmount": 0,
        "renderTime": 0,
        "forcedGcTime": 2.504000000655651,
        "forcedGcAmount": 140.104
      }
    }
  ]
}